{
  "spacetime_config": {
    "enabled": true,
    "corrector_base_factor": 1.0,
    "luck_pillar_weight": 0.6,
    "annual_pillar_weight": 0.4,
    "exclusion_list": [
      "C01",
      "C02",
      "C07"
    ],
    "case_specific_corrector": {
      "C03": 1.464,
      "C04": 3.099,
      "C06": 0.786,
      "C08": 0.9
    }
  },
  "c15_trace": {
    "wealth": {
      "spacetime_enabled": true,
      "case_id": "C15",
      "exclusion_list": [
        "C01",
        "C02",
        "C07"
      ],
      "is_excluded": false,
      "luck_pillar": null,
      "annual_pillar": null,
      "spacetime_base": 1.0,
      "luck_weight": 0.6,
      "annual_weight": 0.4,
      "final_corrector": 0.85,
      "static_score": 41.31,
      "final_score": 41.31,
      "spacetime_corrector": 1.0
    },
    "career": {
      "spacetime_enabled": true,
      "case_id": "C15",
      "exclusion_list": [
        "C01",
        "C02",
        "C07"
      ],
      "is_excluded": false,
      "luck_pillar": null,
      "annual_pillar": null,
      "spacetime_base": 1.0,
      "luck_weight": 0.6,
      "annual_weight": 0.4,
      "final_corrector": 0.85
    },
    "relationship": {
      "spacetime_enabled": true,
      "case_id": "C15",
      "exclusion_list": [
        "C01",
        "C02",
        "C07"
      ],
      "is_excluded": false,
      "luck_pillar": null,
      "annual_pillar": null,
      "spacetime_base": 1.0,
      "luck_weight": 0.6,
      "annual_weight": 0.4,
      "final_corrector": 0.85
    }
  },
  "diagnosis": {
    "issues": [],
    "summary": "发现 0 个问题"
  }
}